substrateinterface/__init__.py
substrateinterface/constants.py
substrateinterface/exceptions.py
substrateinterface/subkey.py
substrateinterface/utils/__init__.py
substrateinterface/utils/hasher.py
substrateinterface/utils/ss58.py
test/__init__.py
test/fixtures.py
test/settings.py
test/test_create_extrinsics.py
test/test_keypair.py
test/test_runtime_state.py
test/test_type_registry.py
py_substrate_api-0.2.1.dist-info/LICENSE
py_substrate_api-0.2.1.dist-info/METADATA
py_substrate_api-0.2.1.dist-info/WHEEL
py_substrate_api-0.2.1.dist-info/top_level.txt
py_substrate_api-0.2.1.dist-info/RECORD
