Metadata-Version: 2.1
Name: py-substrate-api
Version: 0.2.1
Summary: Library for interfacing with a Substrate node
Home-page: https://github.com/kevinyankai/py-substrate-interface
Author: Kevin
Author-email: 13088966264@163.com
License: UNKNOWN
Keywords: interface polkascan polkadot substrate blockchain rpc
Platform: UNKNOWN
Classifier: Development Status :: 4 - Beta
Classifier: Intended Audience :: Developers
Classifier: License :: OSI Approved :: GNU General Public License v3 or later (GPLv3+)
Classifier: Programming Language :: Python :: 3
Classifier: Programming Language :: Python :: 3.7
Classifier: Programming Language :: Python :: 3.8
Requires-Python: >=3.6, <4
Requires-Dist: asyncio (==3.4.3)
Requires-Dist: websockets (==8.1)
Requires-Dist: base58 (==1.0.3)
Requires-Dist: certifi (==2019.6.16)
Requires-Dist: chardet (==3.0.4)
Requires-Dist: docker (==4.2.0)
Requires-Dist: idna (==2.8)
Requires-Dist: requests (==2.22.0)
Requires-Dist: urllib3 (==1.25.3)
Requires-Dist: xxhash (==1.3.0)
Requires-Dist: scalecodec (>=0.9.56)
Requires-Dist: py-sr25519-bindings (>=0.1.2)
Requires-Dist: py-bip39-bindings (>=0.1.4)
Provides-Extra: test
Requires-Dist: coverage ; extra == 'test'
Requires-Dist: pytest ; extra == 'test'
